apigram/__init__.py
apigram/connection.py
apigram/keyboard.py
apigram-0.0.5.dist-info/LICENSE
apigram-0.0.5.dist-info/METADATA
apigram-0.0.5.dist-info/WHEEL
apigram-0.0.5.dist-info/top_level.txt
apigram-0.0.5.dist-info/RECORD
