Metadata-Version: 2.1
Name: apigram
Version: 0.0.5
Summary: Python library to make bot with Telegram Bot API
Home-page: https://github.com/andprokofieff/apigram
Author: andprokofieff
Author-email: prokofieff.help@gmail.com
License: UNKNOWN
Platform: UNKNOWN
Classifier: Programming Language :: Python :: 3
Classifier: License :: OSI Approved :: Apache Software License
Classifier: Operating System :: OS Independent
Requires-Python: >=3.4
Requires-Dist: requests
Requires-Dist: six
Requires-Dist: enum34 ; python_version < "3.4"
